sntools/__init__.py
sntools/channel.py
sntools/detectors.py
sntools/event.py
sntools/genevts.py
sntools/transformation.py
sntools/formats/__init__.py
sntools/formats/gamma.py
sntools/formats/nakazato.py
sntools/formats/princeton.py
sntools/formats/totani.py
sntools/formats/warren2020.py
sntools/interaction_channels/__init__.py
sntools/interaction_channels/c12e.py
sntools/interaction_channels/c12eb.py
sntools/interaction_channels/c12nc.py
sntools/interaction_channels/es.py
sntools/interaction_channels/ibd.py
sntools/interaction_channels/o16e.py
sntools/interaction_channels/o16eb.py
sntools/interaction_channels/ps.py
sntools-1.4.dist-info/LICENSE.md
sntools-1.4.dist-info/METADATA
sntools-1.4.dist-info/WHEEL
sntools-1.4.dist-info/entry_points.txt
sntools-1.4.dist-info/top_level.txt
sntools-1.4.dist-info/RECORD
