Metadata-Version: 2.1
Name: sntools
Version: 1.4
Summary: Event generator for supernova burst neutrinos
Author: Jost Migenda, sntools Contributors
Project-URL: Homepage, https://github.com/SNEWS2/sntools
Project-URL: Bug Tracker, https://github.com/SNEWS2/sntools/issues
Keywords: astrophysics,supernova,neutrino,event generator
Classifier: License :: OSI Approved :: BSD License
Classifier: Development Status :: 5 - Production/Stable
Classifier: Intended Audience :: Science/Research
Classifier: Topic :: Scientific/Engineering
Classifier: Topic :: Scientific/Engineering :: Astronomy
Classifier: Topic :: Scientific/Engineering :: Physics
Classifier: Natural Language :: English
Classifier: Operating System :: OS Independent
Classifier: Programming Language :: Python :: 3
Classifier: Programming Language :: Python :: 3 :: Only
Classifier: Programming Language :: Python :: 3.8
Classifier: Programming Language :: Python :: 3.9
Classifier: Programming Language :: Python :: 3.10
Classifier: Programming Language :: Python :: 3.11
Classifier: Programming Language :: Python :: 3.12
Requires-Python: >=3.8
License-File: LICENSE.md
Requires-Dist: numpy
Requires-Dist: scipy
Requires-Dist: h5py >=2.10
Requires-Dist: snewpy ~=1.5.0
Requires-Dist: uproot
